{
    "n0": [
        {
            "10.0.1.3": {
                "43997": [
                    {
                        "meta": true,
                        "start_time": "0",
                        "stop_time": "20",
                        "destination_node": "n3"
                    },
                    {
                        "timestamp": "1688788552.182033631",
                        "cwnd": "125",
                        "rtt": "0.023",
                        "dev_rtt": "0.012",
                        "ssthresh": "125",
                        "rto": "210",
                        "delivery_rate": "38061.71428",
                        "pacing_rate": "187848.648648"
                    },
                    {
                        "timestamp": "1688788552.388534013",
                        "cwnd": "957",
                        "rtt": "0.038",
                        "dev_rtt": "0.01",
                        "ssthresh": "125",
                        "rto": "210",
                        "delivery_rate": "78192.0",
                        "pacing_rate": "404655.987832"
                    },
                    {
                        "timestamp": "1688788552.592721727",
                        "cwnd": "957",
                        "rtt": "0.036",
                        "dev_rtt": "0.02",
                        "ssthresh": "125",
                        "rto": "210",
                        "delivery_rate": "101817.263152",
                        "pacing_rate": "364467.55068"
                    },
                    {
                        "timestamp": "1688788552.796244260",
                        "cwnd": "957",
                        "rtt": "0.015",
                        "dev_rtt": "0.01",
                        "ssthresh": "125",
                        "rto": "210",
                        "delivery_rate": "68382.967736",
                        "pacing_rate": "1934991.36"
                    },
                    {
                        "timestamp": "1688788553.000472845",
                        "cwnd": "957",
                        "rtt": "0.026",
                        "dev_rtt": "0.004",
                        "ssthresh": "125",
                        "rto": "210",
                        "delivery_rate": "19030.857136",
                        "pacing_rate": "2313576.62608"
                    },
                    {
                        "timestamp": "1688788553.206678521",
                        "cwnd": "957",
                        "rtt": "0.022",
                        "dev_rtt": "0.011",
                        "ssthresh": "125",
                        "rto": "210",
                        "delivery_rate": "38061.71428",
                        "pacing_rate": "2217177.6"
                    },
                    {
                        "timestamp": "1688788553.412122086",
                        "cwnd": "957",
                        "rtt": "0.009",
                        "dev_rtt": "0.006",
                        "ssthresh": "125",
                        "rto": "210",
                        "delivery_rate": "50868.86956",
                        "pacing_rate": "2264351.591488"
                    },
                    {
                        "timestamp": "1688788553.616555754",
                        "cwnd": "957",
                        "rtt": "0.014",
                        "dev_rtt": "0.014",
                        "ssthresh": "125",
                        "rto": "210",
                        "delivery_rate": "50840.888888",
                        "pacing_rate": "2008009.90188"
                    },
                    {
                        "timestamp": "1688788553.820092841",
                        "cwnd": "957",
                        "rtt": "0.024",
                        "dev_rtt": "0",
                        "ssthresh": "125",
                        "rto": "210",
                        "delivery_rate": "13321.6",
                        "pacing_rate": "2171929.077544"
                    },
                    {
                        "timestamp": "1688788554.033510947",
                        "cwnd": "957",
                        "rtt": "0.022",
                        "dev_rtt": "0.003",
                        "ssthresh": "125",
                        "rto": "210",
                        "delivery_rate": "9267.2",
                        "pacing_rate": "2264351.591488"
                    },
                    {
                        "timestamp": "1688788554.238605793",
                        "cwnd": "957",
                        "rtt": "0.023",
                        "dev_rtt": "0.007",
                        "ssthresh": "125",
                        "rto": "210",
                        "delivery_rate": "7316.21052",
                        "pacing_rate": "2217177.6"
                    },
                    {
                        "timestamp": "1688788554.443139185",
                        "cwnd": "957",
                        "rtt": "0.007",
                        "dev_rtt": "0.002",
                        "ssthresh": "125",
                        "rto": "210",
                        "delivery_rate": "46336.0",
                        "pacing_rate": "2217177.6"
                    },
                    {
                        "timestamp": "1688788554.646281342",
                        "cwnd": "957",
                        "rtt": "0.008",
                        "dev_rtt": "0.005",
                        "ssthresh": "125",
                        "rto": "210",
                        "delivery_rate": "34752.0",
                        "pacing_rate": "2128490.496"
                    },
                    {
                        "timestamp": "1688788554.849377562",
                        "cwnd": "957",
                        "rtt": "0.014",
                        "dev_rtt": "0.011",
                        "ssthresh": "125",
                        "rto": "210",
                        "delivery_rate": "45832.347824",
                        "pacing_rate": "2217177.6"
                    },
                    {
                        "timestamp": "1688788555.060170340",
                        "cwnd": "957",
                        "rtt": "0.027",
                        "dev_rtt": "0.008",
                        "ssthresh": "125",
                        "rto": "210",
                        "delivery_rate": "53707.63636",
                        "pacing_rate": "2264351.591488"
                    },
                    {
                        "timestamp": "1688788555.269847272",
                        "cwnd": "957",
                        "rtt": "0.02",
                        "dev_rtt": "0.014",
                        "ssthresh": "125",
                        "rto": "210",
                        "delivery_rate": "38061.71428",
                        "pacing_rate": "2008009.90188"
                    },
                    {
                        "timestamp": "1688788555.472852458",
                        "cwnd": "1186",
                        "rtt": "0.021",
                        "dev_rtt": "0.006",
                        "ssthresh": "125",
                        "rto": "210",
                        "delivery_rate": "14022.73684",
                        "pacing_rate": "2806187.029784"
                    },
                    {
                        "timestamp": "1688788555.677440405",
                        "cwnd": "1186",
                        "rtt": "0.023",
                        "dev_rtt": "0.009",
                        "ssthresh": "125",
                        "rto": "210",
                        "delivery_rate": "49232.0",
                        "pacing_rate": "2747724.8"
                    },
                    {
                        "timestamp": "1688788555.881623934",
                        "cwnd": "1186",
                        "rtt": "0.026",
                        "dev_rtt": "0.005",
                        "ssthresh": "125",
                        "rto": "210",
                        "delivery_rate": "50424.470584",
                        "pacing_rate": "2806187.029784"
                    },
                    {
                        "timestamp": "1688788556.088122052",
                        "cwnd": "1186",
                        "rtt": "0.033",
                        "dev_rtt": "0.016",
                        "ssthresh": "125",
                        "rto": "210",
                        "delivery_rate": "34752.0",
                        "pacing_rate": "2747724.8"
                    },
                    {
                        "timestamp": "1688788556.300425812",
                        "cwnd": "1186",
                        "rtt": "0.015",
                        "dev_rtt": "0.006",
                        "ssthresh": "125",
                        "rto": "210",
                        "delivery_rate": "43662.769224",
                        "pacing_rate": "2806187.029784"
                    },
                    {
                        "timestamp": "1688788556.506266435",
                        "cwnd": "1186",
                        "rtt": "0.025",
                        "dev_rtt": "0",
                        "ssthresh": "125",
                        "rto": "210",
                        "delivery_rate": "9929.142856",
                        "pacing_rate": "1884154.148568"
                    },
                    {
                        "timestamp": "1688788556.713743339",
                        "cwnd": "1307",
                        "rtt": "0.039",
                        "dev_rtt": "0.023",
                        "ssthresh": "125",
                        "rto": "210",
                        "delivery_rate": "73029.565216",
                        "pacing_rate": "455632.491536"
                    },
                    {
                        "timestamp": "1688788556.919630028",
                        "cwnd": "1307",
                        "rtt": "0.236",
                        "dev_rtt": "0.306",
                        "ssthresh": "125",
                        "rto": "210",
                        "delivery_rate": "28878.422528",
                        "pacing_rate": "76781.175272"
                    },
                    {
                        "timestamp": "1688788557.126045032",
                        "cwnd": "1307",
                        "rtt": "0.026",
                        "dev_rtt": "0.004",
                        "ssthresh": "125",
                        "rto": "210",
                        "delivery_rate": "6619.428568",
                        "pacing_rate": "1371195.894336"
                    },
                    {
                        "timestamp": "1688788557.331672516",
                        "cwnd": "1307",
                        "rtt": "0.023",
                        "dev_rtt": "0.008",
                        "ssthresh": "979",
                        "rto": "210",
                        "delivery_rate": "34752.0",
                        "pacing_rate": "3092484.35744"
                    },
                    {
                        "timestamp": "1688788557.539641361",
                        "cwnd": "1307",
                        "rtt": "0.032",
                        "dev_rtt": "0.015",
                        "ssthresh": "979",
                        "rto": "210",
                        "delivery_rate": "38061.71428",
                        "pacing_rate": "3028057.6"
                    },
                    {
                        "timestamp": "1688788557.746253513",
                        "cwnd": "1307",
                        "rtt": "0.026",
                        "dev_rtt": "0.004",
                        "ssthresh": "979",
                        "rto": "210",
                        "delivery_rate": "9929.142856",
                        "pacing_rate": "2742391.788672"
                    },
                    {
                        "timestamp": "1688788557.970396915",
                        "cwnd": "1307",
                        "rtt": "0.025",
                        "dev_rtt": "0.002",
                        "ssthresh": "979",
                        "rto": "210",
                        "delivery_rate": "49232.0",
                        "pacing_rate": "3092484.35744"
                    },
                    {
                        "timestamp": "1688788558.177129545",
                        "cwnd": "1307",
                        "rtt": "0.024",
                        "dev_rtt": "0",
                        "ssthresh": "979",
                        "rto": "210",
                        "delivery_rate": "79384.470584",
                        "pacing_rate": "3028057.6"
                    },
                    {
                        "timestamp": "1688788558.382988945",
                        "cwnd": "1307",
                        "rtt": "0.008",
                        "dev_rtt": "0.003",
                        "ssthresh": "979",
                        "rto": "210",
                        "delivery_rate": "38061.71428",
                        "pacing_rate": "2271043.2"
                    },
                    {
                        "timestamp": "1688788558.586019729",
                        "cwnd": "1307",
                        "rtt": "0.026",
                        "dev_rtt": "0.004",
                        "ssthresh": "979",
                        "rto": "210",
                        "delivery_rate": "9929.142856",
                        "pacing_rate": "2595477.942856"
                    },
                    {
                        "timestamp": "1688788558.795621532",
                        "cwnd": "1307",
                        "rtt": "0.025",
                        "dev_rtt": "0.003",
                        "ssthresh": "979",
                        "rto": "210",
                        "delivery_rate": "8205.333328",
                        "pacing_rate": "3028057.6"
                    },
                    {
                        "timestamp": "1688788559.009967126",
                        "cwnd": "1307",
                        "rtt": "0.01",
                        "dev_rtt": "0.007",
                        "ssthresh": "979",
                        "rto": "210",
                        "delivery_rate": "39716.571424",
                        "pacing_rate": "2076382.35428"
                    },
                    {
                        "timestamp": "1688788559.215421486",
                        "cwnd": "1307",
                        "rtt": "0.023",
                        "dev_rtt": "0.006",
                        "ssthresh": "979",
                        "rto": "210",
                        "delivery_rate": "10692.923072",
                        "pacing_rate": "1991051.5726"
                    },
                    {
                        "timestamp": "1688788559.419459425",
                        "cwnd": "1307",
                        "rtt": "0.028",
                        "dev_rtt": "0.008",
                        "ssthresh": "979",
                        "rto": "210",
                        "delivery_rate": "51484.44444",
                        "pacing_rate": "2505978.703448"
                    },
                    {
                        "timestamp": "1688788559.629433584",
                        "cwnd": "1307",
                        "rtt": "0.025",
                        "dev_rtt": "0.001",
                        "ssthresh": "979",
                        "rto": "210",
                        "delivery_rate": "7316.21052",
                        "pacing_rate": "2595477.942856"
                    },
                    {
                        "timestamp": "1688788559.840745462",
                        "cwnd": "1307",
                        "rtt": "0.008",
                        "dev_rtt": "0.004",
                        "ssthresh": "979",
                        "rto": "210",
                        "delivery_rate": "44405.333328",
                        "pacing_rate": "3092484.35744"
                    },
                    {
                        "timestamp": "1688788560.043794499",
                        "cwnd": "1307",
                        "rtt": "0.023",
                        "dev_rtt": "0.003",
                        "ssthresh": "979",
                        "rto": "210",
                        "delivery_rate": "50791.384608",
                        "pacing_rate": "2505978.703448"
                    },
                    {
                        "timestamp": "1688788560.246958331",
                        "cwnd": "1307",
                        "rtt": "0.009",
                        "dev_rtt": "0.004",
                        "ssthresh": "979",
                        "rto": "210",
                        "delivery_rate": "44405.333328",
                        "pacing_rate": "3092484.35744"
                    },
                    {
                        "timestamp": "1688788560.456001707",
                        "cwnd": "1307",
                        "rtt": "0.026",
                        "dev_rtt": "0.005",
                        "ssthresh": "979",
                        "rto": "210",
                        "delivery_rate": "38061.71428",
                        "pacing_rate": "807482.026664"
                    },
                    {
                        "timestamp": "1688788560.666494286",
                        "cwnd": "1307",
                        "rtt": "0.008",
                        "dev_rtt": "0.004",
                        "ssthresh": "979",
                        "rto": "210",
                        "delivery_rate": "50840.888888",
                        "pacing_rate": "3028057.6"
                    },
                    {
                        "timestamp": "1688788560.870263993",
                        "cwnd": "1307",
                        "rtt": "0.02",
                        "dev_rtt": "0.007",
                        "ssthresh": "979",
                        "rto": "210",
                        "delivery_rate": "19858.285712",
                        "pacing_rate": "3092484.35744"
                    },
                    {
                        "timestamp": "1688788561.074597700",
                        "cwnd": "1307",
                        "rtt": "0.023",
                        "dev_rtt": "0.007",
                        "ssthresh": "979",
                        "rto": "210",
                        "delivery_rate": "14801.777776",
                        "pacing_rate": "3028057.6"
                    },
                    {
                        "timestamp": "1688788561.278674289",
                        "cwnd": "1307",
                        "rtt": "0.016",
                        "dev_rtt": "0.01",
                        "ssthresh": "979",
                        "rto": "210",
                        "delivery_rate": "48983.771424",
                        "pacing_rate": "3028057.6"
                    },
                    {
                        "timestamp": "1688788561.481781038",
                        "cwnd": "1307",
                        "rtt": "0.024",
                        "dev_rtt": "0.002",
                        "ssthresh": "979",
                        "rto": "210",
                        "delivery_rate": "6318.545448",
                        "pacing_rate": "1118052.03692"
                    },
                    {
                        "timestamp": "1688788561.687545968",
                        "cwnd": "1307",
                        "rtt": "0.028",
                        "dev_rtt": "0.006",
                        "ssthresh": "979",
                        "rto": "210",
                        "delivery_rate": "47389.090904",
                        "pacing_rate": "2691606.755552"
                    },
                    {
                        "timestamp": "1688788561.891232741",
                        "cwnd": "1307",
                        "rtt": "0.011",
                        "dev_rtt": "0.008",
                        "ssthresh": "979",
                        "rto": "210",
                        "delivery_rate": "51714.285712",
                        "pacing_rate": "3092484.35744"
                    },
                    {
                        "timestamp": "1688788562.100110590",
                        "cwnd": "1307",
                        "rtt": "0.024",
                        "dev_rtt": "0.001",
                        "ssthresh": "979",
                        "rto": "210",
                        "delivery_rate": "50840.888888",
                        "pacing_rate": "3092484.35744"
                    },
                    {
                        "timestamp": "1688788562.305677735",
                        "cwnd": "1307",
                        "rtt": "0.01",
                        "dev_rtt": "0.005",
                        "ssthresh": "979",
                        "rto": "210",
                        "delivery_rate": "49232.0",
                        "pacing_rate": "3028057.6"
                    },
                    {
                        "timestamp": "1688788562.510121036",
                        "cwnd": "1307",
                        "rtt": "0.024",
                        "dev_rtt": "0",
                        "ssthresh": "979",
                        "rto": "210",
                        "delivery_rate": "52707.2",
                        "pacing_rate": "2742391.788672"
                    },
                    {
                        "timestamp": "1688788562.715539106",
                        "cwnd": "1307",
                        "rtt": "0.024",
                        "dev_rtt": "0.001",
                        "ssthresh": "979",
                        "rto": "210",
                        "delivery_rate": "6950.4",
                        "pacing_rate": "3028057.6"
                    },
                    {
                        "timestamp": "1688788562.922164020",
                        "cwnd": "1307",
                        "rtt": "0.03",
                        "dev_rtt": "0.014",
                        "ssthresh": "979",
                        "rto": "210",
                        "delivery_rate": "44405.333328",
                        "pacing_rate": "3028057.6"
                    },
                    {
                        "timestamp": "1688788563.128846452",
                        "cwnd": "1307",
                        "rtt": "0.01",
                        "dev_rtt": "0.007",
                        "ssthresh": "979",
                        "rto": "210",
                        "delivery_rate": "44405.333328",
                        "pacing_rate": "3028057.6"
                    },
                    {
                        "timestamp": "1688788563.332424104",
                        "cwnd": "1307",
                        "rtt": "0.013",
                        "dev_rtt": "0.01",
                        "ssthresh": "979",
                        "rto": "210",
                        "delivery_rate": "46336.0",
                        "pacing_rate": "3028057.6"
                    },
                    {
                        "timestamp": "1688788563.535976014",
                        "cwnd": "1307",
                        "rtt": "0.027",
                        "dev_rtt": "0.007",
                        "ssthresh": "979",
                        "rto": "210",
                        "delivery_rate": "9867.851848",
                        "pacing_rate": "3092484.35744"
                    },
                    {
                        "timestamp": "1688788563.749884784",
                        "cwnd": "1307",
                        "rtt": "0.026",
                        "dev_rtt": "0.008",
                        "ssthresh": "979",
                        "rto": "210",
                        "delivery_rate": "8326.0",
                        "pacing_rate": "2966260.50612"
                    },
                    {
                        "timestamp": "1688788563.952817382",
                        "cwnd": "1307",
                        "rtt": "0.006",
                        "dev_rtt": "0",
                        "ssthresh": "979",
                        "rto": "210",
                        "delivery_rate": "50345.846152",
                        "pacing_rate": "3028057.6"
                    },
                    {
                        "timestamp": "1688788564.155358571",
                        "cwnd": "1307",
                        "rtt": "0.007",
                        "dev_rtt": "0.003",
                        "ssthresh": "979",
                        "rto": "210",
                        "delivery_rate": "48774.73684",
                        "pacing_rate": "2307091.50476"
                    },
                    {
                        "timestamp": "1688788564.358070356",
                        "cwnd": "1307",
                        "rtt": "0.026",
                        "dev_rtt": "0.004",
                        "ssthresh": "979",
                        "rto": "210",
                        "delivery_rate": "48774.73684",
                        "pacing_rate": "2795130.092304"
                    },
                    {
                        "timestamp": "1688788564.562665801",
                        "cwnd": "1307",
                        "rtt": "0.008",
                        "dev_rtt": "0.004",
                        "ssthresh": "979",
                        "rto": "210",
                        "delivery_rate": "50791.384608",
                        "pacing_rate": "3092484.35744"
                    },
                    {
                        "timestamp": "1688788564.765785178",
                        "cwnd": "1307",
                        "rtt": "0.025",
                        "dev_rtt": "0.001",
                        "ssthresh": "979",
                        "rto": "210",
                        "delivery_rate": "48774.73684",
                        "pacing_rate": "3028057.6"
                    },
                    {
                        "timestamp": "1688788564.975777835",
                        "cwnd": "1307",
                        "rtt": "0.008",
                        "dev_rtt": "0.004",
                        "ssthresh": "979",
                        "rto": "210",
                        "delivery_rate": "38061.71428",
                        "pacing_rate": "3092484.35744"
                    },
                    {
                        "timestamp": "1688788565.183743990",
                        "cwnd": "1307",
                        "rtt": "0.027",
                        "dev_rtt": "0.008",
                        "ssthresh": "979",
                        "rto": "210",
                        "delivery_rate": "52823.04",
                        "pacing_rate": "3092484.35744"
                    },
                    {
                        "timestamp": "1688788565.386597110",
                        "cwnd": "1307",
                        "rtt": "0.012",
                        "dev_rtt": "0.011",
                        "ssthresh": "979",
                        "rto": "210",
                        "delivery_rate": "51372.521736",
                        "pacing_rate": "3092484.35744"
                    },
                    {
                        "timestamp": "1688788565.589467202",
                        "cwnd": "642",
                        "rtt": "0.017",
                        "dev_rtt": "0.006",
                        "ssthresh": "642",
                        "rto": "210",
                        "delivery_rate": "14801.777776",
                        "pacing_rate": "1487385.6"
                    },
                    {
                        "timestamp": "1688788565.793462253",
                        "cwnd": "642",
                        "rtt": "0.029",
                        "dev_rtt": "0.01",
                        "ssthresh": "642",
                        "rto": "210",
                        "delivery_rate": "29603.555552",
                        "pacing_rate": "1230939.806896"
                    },
                    {
                        "timestamp": "1688788566.000117390",
                        "cwnd": "837",
                        "rtt": "0.024",
                        "dev_rtt": "0.002",
                        "ssthresh": "642",
                        "rto": "210",
                        "delivery_rate": "38061.71428",
                        "pacing_rate": "1980420.35744"
                    },
                    {
                        "timestamp": "1688788566.209707192",
                        "cwnd": "837",
                        "rtt": "0.028",
                        "dev_rtt": "0.01",
                        "ssthresh": "642",
                        "rto": "210",
                        "delivery_rate": "9606.243896",
                        "pacing_rate": "1861595.136"
                    },
                    {
                        "timestamp": "1688788566.412925364",
                        "cwnd": "837",
                        "rtt": "0.028",
                        "dev_rtt": "0.009",
                        "ssthresh": "642",
                        "rto": "210",
                        "delivery_rate": "51484.44444",
                        "pacing_rate": "1525897.652456"
                    },
                    {
                        "timestamp": "1688788566.619813449",
                        "cwnd": "837",
                        "rtt": "0.024",
                        "dev_rtt": "0.001",
                        "ssthresh": "642",
                        "rto": "210",
                        "delivery_rate": "38061.71428",
                        "pacing_rate": "1551329.28"
                    },
                    {
                        "timestamp": "1688788566.828524427",
                        "cwnd": "837",
                        "rtt": "0.026",
                        "dev_rtt": "0.003",
                        "ssthresh": "642",
                        "rto": "210",
                        "delivery_rate": "9929.142856",
                        "pacing_rate": "1980420.35744"
                    },
                    {
                        "timestamp": "1688788567.054312183",
                        "cwnd": "837",
                        "rtt": "0.029",
                        "dev_rtt": "0.009",
                        "ssthresh": "642",
                        "rto": "210",
                        "delivery_rate": "34752.0",
                        "pacing_rate": "1825093.270584"
                    },
                    {
                        "timestamp": "1688788567.259682521",
                        "cwnd": "837",
                        "rtt": "0.026",
                        "dev_rtt": "0.003",
                        "ssthresh": "642",
                        "rto": "210",
                        "delivery_rate": "7316.21052",
                        "pacing_rate": "1861595.136"
                    },
                    {
                        "timestamp": "1688788567.469414474",
                        "cwnd": "837",
                        "rtt": "0.006",
                        "dev_rtt": "0",
                        "ssthresh": "642",
                        "rto": "210",
                        "delivery_rate": "51714.285712",
                        "pacing_rate": "1939161.6"
                    },
                    {
                        "timestamp": "1688788567.671873577",
                        "cwnd": "837",
                        "rtt": "0.027",
                        "dev_rtt": "0.005",
                        "ssthresh": "642",
                        "rto": "210",
                        "delivery_rate": "34752.0",
                        "pacing_rate": "1939161.6"
                    },
                    {
                        "timestamp": "1688788567.889835676",
                        "cwnd": "837",
                        "rtt": "0.01",
                        "dev_rtt": "0.007",
                        "ssthresh": "642",
                        "rto": "210",
                        "delivery_rate": "38061.71428",
                        "pacing_rate": "1939161.6"
                    },
                    {
                        "timestamp": "1688788568.100340922",
                        "cwnd": "837",
                        "rtt": "0.025",
                        "dev_rtt": "0.004",
                        "ssthresh": "642",
                        "rto": "210",
                        "delivery_rate": "47163.428568",
                        "pacing_rate": "1980420.35744"
                    },
                    {
                        "timestamp": "1688788568.307610249",
                        "cwnd": "837",
                        "rtt": "0.026",
                        "dev_rtt": "0.004",
                        "ssthresh": "642",
                        "rto": "210",
                        "delivery_rate": "12705.032256",
                        "pacing_rate": "1939161.6"
                    },
                    {
                        "timestamp": "1688788568.540192035",
                        "cwnd": "837",
                        "rtt": "0.018",
                        "dev_rtt": "0.017",
                        "ssthresh": "642",
                        "rto": "210",
                        "delivery_rate": "48165.052624",
                        "pacing_rate": "1939161.6"
                    },
                    {
                        "timestamp": "1688788568.746103139",
                        "cwnd": "837",
                        "rtt": "0.028",
                        "dev_rtt": "0.006",
                        "ssthresh": "642",
                        "rto": "210",
                        "delivery_rate": "10657.28",
                        "pacing_rate": "1980420.35744"
                    },
                    {
                        "timestamp": "1688788568.960029161",
                        "cwnd": "837",
                        "rtt": "0.015",
                        "dev_rtt": "0.008",
                        "ssthresh": "642",
                        "rto": "210",
                        "delivery_rate": "38061.71428",
                        "pacing_rate": "1692359.214544"
                    },
                    {
                        "timestamp": "1688788569.181788318",
                        "cwnd": "837",
                        "rtt": "0.064",
                        "dev_rtt": "0.028",
                        "ssthresh": "642",
                        "rto": "210",
                        "delivery_rate": "29016.233008",
                        "pacing_rate": "180038.214312"
                    },
                    {
                        "timestamp": "1688788569.387346490",
                        "cwnd": "837",
                        "rtt": "0.034",
                        "dev_rtt": "0.018",
                        "ssthresh": "642",
                        "rto": "210",
                        "delivery_rate": "62264.0",
                        "pacing_rate": "336028.002888"
                    },
                    {
                        "timestamp": "1688788569.591238497",
                        "cwnd": "837",
                        "rtt": "0.03",
                        "dev_rtt": "0.014",
                        "ssthresh": "642",
                        "rto": "210",
                        "delivery_rate": "93315.555552",
                        "pacing_rate": "387832.32"
                    },
                    {
                        "timestamp": "1688788569.796267319",
                        "cwnd": "837",
                        "rtt": "0.086",
                        "dev_rtt": "0.054",
                        "ssthresh": "642",
                        "rto": "210",
                        "delivery_rate": "48652.8",
                        "pacing_rate": "134120.687024"
                    },
                    {
                        "timestamp": "1688788570.001911973",
                        "cwnd": "837",
                        "rtt": "0.036",
                        "dev_rtt": "0.014",
                        "ssthresh": "642",
                        "rto": "210",
                        "delivery_rate": "98804.70588",
                        "pacing_rate": "319861.707216"
                    },
                    {
                        "timestamp": "1688788570.205173333",
                        "cwnd": "837",
                        "rtt": "0.02",
                        "dev_rtt": "0.007",
                        "ssthresh": "642",
                        "rto": "210",
                        "delivery_rate": "14022.73684",
                        "pacing_rate": "1368819.952936"
                    },
                    {
                        "timestamp": "1688788570.409567869",
                        "cwnd": "844",
                        "rtt": "0.031",
                        "dev_rtt": "0.014",
                        "ssthresh": "642",
                        "rto": "210",
                        "delivery_rate": "46336.0",
                        "pacing_rate": "1955379.2"
                    },
                    {
                        "timestamp": "1688788570.614064611",
                        "cwnd": "844",
                        "rtt": "0.031",
                        "dev_rtt": "0.016",
                        "ssthresh": "642",
                        "rto": "210",
                        "delivery_rate": "29603.555552",
                        "pacing_rate": "1915473.50204"
                    },
                    {
                        "timestamp": "1688788570.827101157",
                        "cwnd": "844",
                        "rtt": "0.022",
                        "dev_rtt": "0.01",
                        "ssthresh": "642",
                        "rto": "210",
                        "delivery_rate": "47163.428568",
                        "pacing_rate": "1955379.2"
                    },
                    {
                        "timestamp": "1688788571.030185505",
                        "cwnd": "844",
                        "rtt": "0.024",
                        "dev_rtt": "0",
                        "ssthresh": "642",
                        "rto": "210",
                        "delivery_rate": "10644.756752",
                        "pacing_rate": "1955379.2"
                    },
                    {
                        "timestamp": "1688788571.239804543",
                        "cwnd": "844",
                        "rtt": "0.02",
                        "dev_rtt": "0.01",
                        "ssthresh": "642",
                        "rto": "210",
                        "delivery_rate": "47262.72",
                        "pacing_rate": "1706512.75636"
                    },
                    {
                        "timestamp": "1688788571.442756481",
                        "cwnd": "844",
                        "rtt": "0.022",
                        "dev_rtt": "0.006",
                        "ssthresh": "642",
                        "rto": "210",
                        "delivery_rate": "50791.384608",
                        "pacing_rate": "1955379.2"
                    },
                    {
                        "timestamp": "1688788571.646568293",
                        "cwnd": "844",
                        "rtt": "0.007",
                        "dev_rtt": "0.004",
                        "ssthresh": "642",
                        "rto": "210",
                        "delivery_rate": "47163.428568",
                        "pacing_rate": "1955379.2"
                    },
                    {
                        "timestamp": "1688788571.849314582",
                        "cwnd": "844",
                        "rtt": "0.024",
                        "dev_rtt": "0",
                        "ssthresh": "642",
                        "rto": "210",
                        "delivery_rate": "9929.142856",
                        "pacing_rate": "1955379.2"
                    }
                ]
            }
        }
    ]
}